eevalue/__init__.py
eevalue/eevalue.py
eevalue-2.1.0.dist-info/licenses/LICENSE
eevalue-2.1.0.dist-info/METADATA
eevalue-2.1.0.dist-info/WHEEL
eevalue-2.1.0.dist-info/top_level.txt
eevalue-2.1.0.dist-info/RECORD
