Metadata-Version: 2.4
Name: eevalue
Version: 2.1.0
Summary: A package that easily lets you find nearest E-series values and printing values with Si prefixes.
Home-page: https://github.com/Duckle29/EEValue
Author: Mikkel Jeppesen
Author-email: mikkel+pypi@mikkel.cc
Project-URL: Bug Tracker, https://github.com/Duckle29/EEvalue/issues
Classifier: Programming Language :: Python :: 3
Classifier: License :: OSI Approved :: BSD License
Classifier: Operating System :: OS Independent
Requires-Python: >=3.6
License-File: LICENSE
Dynamic: license-file
